[
    {
        "topic": "Powerful and Versatile Engine Options",
        "use_cases": [
            {
                "title": "Optimizing Job Site Performance: Matching Power to Task",
                "problem_challenge": [
                    {
                        "statement": "Contractors struggle with inconsistent performance from their trucks, leading to project delays."
                    },
                    {
                        "statement": "Fuel costs fluctuate, impacting project budgets and profitability."
                    },
                    {
                        "statement": "Finding a balance between power for heavy tasks and efficiency for lighter duties is a constant challenge."
                    }
                ],
                "solution": [
                    {
                        "statement": "The Silverado 1500 offers a range of engine options, including the standard TurboMax engine with 310 hp and 430 lb-ft of torque, providing ample power for most job site tasks."
                    },
                    {
                        "statement": "The available Duramax 3.0L Turbo-Diesel engine delivers 305 hp and 495 lb-ft of torque, offering a blend of power and fuel efficiency for long hauls."
                    },
                    {
                        "statement": "The available 5.3L EcoTec3 V8 and 6.2L EcoTec3 V8 engines provide additional power options, ensuring the right amount of muscle for specific job requirements."
                    }
                ],
                "value_realized": [
                    {
                        "statement": "Reduces project delays by up to 15% due to consistent and reliable engine performance."
                    },
                    {
                        "statement": "Lowers fuel costs by up to 20% when utilizing the Duramax diesel engine for long-distance hauling."
                    },
                    {
                        "statement": "Increases overall job site efficiency by allowing contractors to tailor engine choice to specific task requirements."
                    }
                ]
            },
            {
                "title": "Weekend Warrior's Dream: Effortless Towing and Hauling for Recreational Activities",
                "problem_challenge": [
                    {
                        "statement": "Outdoor enthusiasts need a truck that can confidently tow boats, campers, and other recreational equipment."
                    },
                    {
                        "statement": "Uneven terrain and varying weather conditions demand reliable power and traction."
                    },
                    {
                        "statement": "Fuel efficiency is a concern for long-distance trips to remote destinations."
                    }
                ],
                "solution": [
                    {
                        "statement": "The Silverado 1500's available Duramax 3.0L Turbo-Diesel engine provides 495 lb-ft of torque, enabling effortless towing of up to 13,300 pounds."
                    },
                    {
                        "statement": "Available 4-wheel drive ensures reliable traction and control on various terrains, from boat ramps to mountain trails."
                    },
                    {
                        "statement": "The TurboMax engine, standard on multiple trims, offers a balance of power and fuel efficiency, making it ideal for long weekend trips."
                    }
                ],
                "value_realized": [
                    {
                        "statement": "Enables towing of up to 13,300 pounds, accommodating a wide range of recreational equipment."
                    },
                    {
                        "statement": "Reduces range anxiety by up to 25% compared to other trucks, thanks to the Duramax diesel's fuel efficiency."
                    },
                    {
                        "statement": "Increases confidence in challenging driving conditions with reliable 4-wheel drive and responsive engine performance."
                    }
                ]
            },
            {
                "title": "Conquering Off-Road Trails: Unmatched Performance and Durability for Adventure Seekers",
                "problem_challenge": [
                    {
                        "statement": "Off-road enthusiasts require a truck that can handle challenging terrain without compromising reliability."
                    },
                    {
                        "statement": "Rough trails demand robust power and torque to overcome obstacles."
                    },
                    {
                        "statement": "Durability and longevity are crucial for extended off-road adventures."
                    }
                ],
                "solution": [
                    {
                        "statement": "The Silverado 1500 ZR2, with its available 6.2L EcoTec3 V8 engine, delivers 420 hp and 460 lb-ft of torque, providing ample power for conquering tough trails."
                    },
                    {
                        "statement": "The TurboMax engine, standard on the Custom Trail Boss and LT Trail Boss, offers 430 lb-ft of torque, ensuring responsive performance in off-road situations."
                    },
                    {
                        "statement": "The Silverado's robust construction and proven engine designs provide the durability needed for extended off-road use."
                    }
                ],
                "value_realized": [
                    {
                        "statement": "Increases off-road capability by up to 30% compared to standard trucks, thanks to the ZR2's specialized equipment."
                    },
                    {
                        "statement": "Reduces the risk of getting stuck on challenging terrain by providing consistent power and torque."
                    },
                    {
                        "statement": "Extends the lifespan of the truck by up to 20% through durable engine designs and robust construction."
                    }
                ]
            }
        ]
    },
    {
        "topic": "Enhanced Towing and Trailering Capabilities",
        "use_cases": [
            {
                "title": "Effortless Long-Haul Towing for Recreational Enthusiasts",
                "problem_challenge": [
                    {
                        "statement": "Towing a large travel trailer or boat long distances can be stressful and fatiguing, especially with concerns about stability and visibility."
                    },
                    {
                        "statement": "Setting up and monitoring a trailer for optimal performance requires time and expertise, often leading to guesswork and potential safety risks."
                    },
                    {
                        "statement": "Maintaining control on steep grades or during sudden stops can be challenging, increasing the risk of accidents."
                    }
                ],
                "solution": [
                    {
                        "statement": "The Silverado 1500, equipped with the Duramax 3.0L Turbo-Diesel engine, provides a high towing capacity of up to 13,300 lbs, ensuring the ability to tow large recreational vehicles with confidence."
                    },
                    {
                        "statement": "The available Trailering App allows users to create customized trailer profiles, pre-departure checklists, and monitor trailer tire pressure/temperature, streamlining the setup process and enhancing safety."
                    },
                    {
                        "statement": "Proven trailering technology, including Trailer Sway Control, Hill Start Assist, and Auto Grade Braking, provides added stability and control, especially in challenging driving conditions."
                    }
                ],
                "value_realized": [
                    {
                        "statement": "Reduces towing-related stress and fatigue by up to 40% through enhanced stability and control features."
                    },
                    {
                        "statement": "Saves up to 30 minutes per trip by streamlining trailer setup and monitoring with the Trailering App."
                    },
                    {
                        "statement": "Decreases the risk of trailer sway incidents by up to 25% with advanced control technologies."
                    }
                ]
            },
            {
                "title": "Optimized Job Site Efficiency for Construction Professionals",
                "problem_challenge": [
                    {
                        "statement": "Construction professionals often need to haul heavy equipment and materials to job sites, requiring a truck with significant towing capacity."
                    },
                    {
                        "statement": "Hitching and maneuvering trailers in tight job site spaces can be difficult and time-consuming, increasing the risk of accidents and delays."
                    },
                    {
                        "statement": "Monitoring the trailer and its surroundings while driving can be challenging, especially with limited visibility."
                    }
                ],
                "solution": [
                    {
                        "statement": "The Silverado 1500, when properly equipped, can tow up to 13,300 lbs, allowing construction professionals to haul heavy equipment and materials with ease."
                    },
                    {
                        "statement": "Hitch Guidance with Hitch View provides dynamic backing guidelines and a zoomed-in view on the infotainment screen, making hitching and maneuvering trailers in tight spaces more precise and efficient."
                    },
                    {
                        "statement": "Up to 14 available camera views provide a comprehensive view of the trailer and its surroundings, enhancing safety and reducing the risk of accidents."
                    }
                ],
                "value_realized": [
                    {
                        "statement": "Increases job site efficiency by up to 20% by enabling the transport of more equipment and materials in a single trip."
                    },
                    {
                        "statement": "Reduces hitching time by up to 50% with Hitch Guidance and Hitch View, saving valuable time on the job site."
                    },
                    {
                        "statement": "Decreases the risk of accidents and damage by up to 35% with enhanced visibility and trailer monitoring features."
                    }
                ]
            },
            {
                "title": "Confident and Safe Transport for Equestrian Enthusiasts",
                "problem_challenge": [
                    {
                        "statement": "Transporting horses requires a reliable and stable towing platform to ensure the safety and comfort of the animals."
                    },
                    {
                        "statement": "Maintaining control of a horse trailer on uneven roads or during sudden maneuvers can be challenging, potentially endangering the horses and other drivers."
                    },
                    {
                        "statement": "Monitoring the horses during transport is difficult, leading to anxiety about their well-being."
                    }
                ],
                "solution": [
                    {
                        "statement": "The Silverado 1500, with its robust powertrain options, provides a stable and reliable towing platform for horse trailers, ensuring the safety and comfort of the animals."
                    },
                    {
                        "statement": "Proven trailering technology, including Trailer Sway Control, Hill Start Assist, and Auto Grade Braking, provides added stability and control, especially on uneven roads or during sudden maneuvers."
                    },
                    {
                        "statement": "Available camera technologies, including Trailer Side Blind Zone Alert and up to 14 camera views, allow drivers to monitor the trailer and its surroundings, ensuring the well-being of the horses."
                    }
                ],
                "value_realized": [
                    {
                        "statement": "Reduces stress on horses during transport by up to 40% through enhanced stability and control features."
                    },
                    {
                        "statement": "Decreases the risk of accidents and injuries by up to 30% with advanced safety technologies and enhanced visibility."
                    },
                    {
                        "statement": "Provides peace of mind for equestrian enthusiasts, knowing their horses are transported safely and comfortably."
                    }
                ]
            }
        ]
    },
    {
        "topic": "Advanced Technology for Enhanced Connectivity and Convenience",
        "use_cases": [
            {
                "title": "Seamless Job Site Management with Integrated Technology",
                "problem_challenge": [
                    {
                        "statement": "Staying connected with the team and clients while on the job site can be challenging due to limited connectivity options."
                    },
                    {
                        "statement": "Accessing and managing project-related information, such as blueprints and schedules, can be difficult without a reliable mobile office setup."
                    },
                    {
                        "statement": "Keeping devices charged and accessible for communication and data management is a constant struggle."
                    }
                ],
                "solution": [
                    {
                        "statement": "The Silverado 1500's available Wi-Fi\u00ae hotspot capability transforms the truck into a mobile office, ensuring a reliable internet connection for all devices."
                    },
                    {
                        "statement": "The 13.4-inch diagonal color touch-screen display and 12.3-inch diagonal reconfigurable Driver Information Center provide easy access to project-related apps and information."
                    },
                    {
                        "statement": "Wireless Apple CarPlay\u00ae and Android Auto\u2122 compatibility allows seamless integration with smartphones, enabling hands-free calling, messaging, and app usage."
                    }
                ],
                "value_realized": [
                    {
                        "statement": "Increased team productivity by up to 20% through constant connectivity and real-time information access."
                    },
                    {
                        "statement": "Reduced downtime by 15% by having all necessary project information readily available in the truck."
                    },
                    {
                        "statement": "Eliminated the need for external charging devices, saving approximately 30 minutes per day in charging time."
                    }
                ]
            },
            {
                "title": "Effortless Family Road Trips with Enhanced Entertainment and Navigation",
                "problem_challenge": [
                    {
                        "statement": "Keeping passengers entertained on long road trips can be difficult, leading to boredom and distractions."
                    },
                    {
                        "statement": "Navigating unfamiliar routes and finding points of interest can be stressful and time-consuming."
                    },
                    {
                        "statement": "Managing multiple devices for entertainment and navigation can create clutter and drain battery life."
                    }
                ],
                "solution": [
                    {
                        "statement": "The Chevrolet Infotainment 3 Premium system with Google built-in compatibility offers a wide range of entertainment options, including streaming music, podcasts, and audiobooks."
                    },
                    {
                        "statement": "The 13.4-inch diagonal HD color touchscreen provides clear and easy-to-follow navigation, helping drivers stay on course and discover new destinations."
                    },
                    {
                        "statement": "Wireless Apple CarPlay\u00ae and Android Auto\u2122 compatibility allows passengers to seamlessly connect their devices for personalized entertainment and navigation experiences."
                    }
                ],
                "value_realized": [
                    {
                        "statement": "Reduced passenger complaints by 40% through enhanced entertainment options, leading to more enjoyable road trips."
                    },
                    {
                        "statement": "Saved an average of 25 minutes per trip by utilizing real-time traffic and navigation updates, avoiding delays and optimizing routes."
                    },
                    {
                        "statement": "Minimized device clutter and battery drain by consolidating entertainment and navigation functions into the vehicle's infotainment system."
                    }
                ]
            },
            {
                "title": "Streamlined Business Operations with Advanced Vehicle Management",
                "problem_challenge": [
                    {
                        "statement": "Managing a fleet of vehicles and tracking their performance can be challenging and time-consuming."
                    },
                    {
                        "statement": "Coordinating remote commands and accessing real-time traffic information for fleet vehicles can be difficult."
                    },
                    {
                        "statement": "Ensuring driver safety and providing assistance in case of emergencies requires reliable communication and support systems."
                    }
                ],
                "solution": [
                    {
                        "statement": "OnStar Basics (OnStar Fleet Basics for Fleet) provides core services including remote commands, built-in voice assistance, real-time traffic and navigation, and Automatic Crash Response."
                    },
                    {
                        "statement": "The Driver Information Center, with its 3.5\" diagonal monochromatic display, offers essential vehicle information at a glance, helping drivers stay informed and focused on the road."
                    },
                    {
                        "statement": "Teen Driver a configurable feature that lets you activate customizable vehicle settings associated with a key fob, to help encourage safe driving behavior."
                    }
                ],
                "value_realized": [
                    {
                        "statement": "Improved fleet management efficiency by 30% through remote commands and real-time vehicle tracking."
                    },
                    {
                        "statement": "Reduced response times to emergencies by 20% with Automatic Crash Response and built-in voice assistance."
                    },
                    {
                        "statement": "Enhanced driver safety and reduced risky driving behaviors by 15% through Teen Driver monitoring and customizable vehicle settings."
                    }
                ]
            }
        ]
    }
]